.env.example
.gitignore
LICENSE
README.md
ingest_files.py
requirements.txt
setup.py
simon/__init__.py
simon/api.py
simon/environment.py
simon/kb.py
simon/models.py
simon/provision.py
simon/schema.sql
simon/search.py
simon/start.py
simon/store.py
simon/agents/__init__.py
simon/agents/querybreaker.py
simon/agents/reason.py
simon/agents/rio.py
simon/components/__init__.py
simon/components/aws.py
simon/components/documents.py
simon/ingestion/__init__.py
simon/ingestion/jsoningester.py
simon/ingestion/ocringester.py
simon/ingestion/textfileingester.py
simon/utils/__init__.py
simon/utils/helpers.py
simon/utils/legacy.py
simon/utils/pdffigures2.jar
simon_search.egg-info/PKG-INFO
simon_search.egg-info/SOURCES.txt
simon_search.egg-info/dependency_links.txt
simon_search.egg-info/entry_points.txt
simon_search.egg-info/requires.txt
simon_search.egg-info/top_level.txt
static/promo.png