Metadata-Version: 2.1
Name: simon-search
Version: 0.0.1.post5
Summary: A pipeline which allows for the ingestion, storage, and processing of a large body of textual information with LLMs.
Author: Shabang Systems, LLC
Author-email: hello@shabang.io
Classifier: Development Status :: 3 - Alpha
Classifier: Topic :: Utilities
Classifier: Natural Language :: English
Classifier: Topic :: Database
Classifier: Topic :: Scientific/Engineering :: Artificial Intelligence
Provides-Extra: web
License-File: LICENSE
